[
  {
    "id": 1,
    "title": "قالب ری اکت شرکتی",
    "text": "لورم ایپسوم متن ساختگی با تولید سادگی نامفهوم از صنعت چاپ و با استفاده از طراحان گرافیک است.",
    "bg": "slider/h-2-01.jpg",
    "btnText": "اطلاعات بیشتر",
    "btnLink": "/about"
  },
  {
    "id": 2,
    "title": "پول خود را هدر ندهید",
    "text": "لورم ایپسوم متن ساختگی با تولید سادگی نامفهوم از صنعت چاپ و با استفاده از طراحان گرافیک است.",
    "bg": "slider/h-2-02.jpg",
    "btnText": "اطلاعات بیشتر",
    "btnLink": "/about"
  }
]
